straw/__init__.py
straw/straw.py
tunnel-1.0.0.dist-info/METADATA
tunnel-1.0.0.dist-info/WHEEL
tunnel-1.0.0.dist-info/top_level.txt
tunnel-1.0.0.dist-info/RECORD
